revhold/__init__.py
revhold/client.py
revhold/exceptions.py
revhold_python-1.0.0.dist-info/licenses/LICENSE
revhold_python-1.0.0.dist-info/METADATA
revhold_python-1.0.0.dist-info/WHEEL
revhold_python-1.0.0.dist-info/top_level.txt
revhold_python-1.0.0.dist-info/RECORD
