Metadata-Version: 2.4
Name: revhold-python
Version: 1.0.0
Summary: Official Python SDK for RevHold - AI business assistant for SaaS analytics
Home-page: https://www.revhold.io
Author: RevHold
Author-email: RevHold <support@revhold.io>
License: MIT
Project-URL: Homepage, https://www.revhold.io
Project-URL: Documentation, https://www.revhold.io/docs
Project-URL: Repository, https://github.com/revhold/python-sdk
Project-URL: Issues, https://github.com/revhold/python-sdk/issues
Keywords: revhold,analytics,saas,ai,usage-tracking,churn-analysis
Classifier: Development Status :: 5 - Production/Stable
Classifier: Intended Audience :: Developers
Classifier: License :: OSI Approved :: MIT License
Classifier: Programming Language :: Python :: 3
Classifier: Programming Language :: Python :: 3.8
Classifier: Programming Language :: Python :: 3.9
Classifier: Programming Language :: Python :: 3.10
Classifier: Programming Language :: Python :: 3.11
Classifier: Programming Language :: Python :: 3.12
Requires-Python: >=3.8
License-File: LICENSE
Requires-Dist: requests>=2.25.0
Provides-Extra: dev
Requires-Dist: pytest>=7.0.0; extra == "dev"
Requires-Dist: pytest-cov>=4.0.0; extra == "dev"
Requires-Dist: black>=22.0.0; extra == "dev"
Requires-Dist: mypy>=0.990; extra == "dev"
Requires-Dist: types-requests>=2.28.0; extra == "dev"
Dynamic: author
Dynamic: home-page
Dynamic: license-file
Dynamic: requires-python
